LICENSE
README.md
setup.py
subx/__init__.py
subx.egg-info/PKG-INFO
subx.egg-info/SOURCES.txt
subx.egg-info/dependency_links.txt
subx.egg-info/top_level.txt