Metadata-Version: 2.1
Name: subx
Version: 2020.43.0
Summary: subx: Datastructure SubprocessResult
Home-page: https://github.com/guettli/subx/
Author: Thomas Guettler
Author-email: info.subx@thomas-guettler.de
License: Apache Software License 2.0
Platform: UNKNOWN
Classifier: Development Status :: 5 - Production/Stable
Classifier: Intended Audience :: Information Technology
Classifier: License :: OSI Approved :: Apache Software License
Classifier: Programming Language :: Python :: 3
Requires-Python: >=3.7
License-File: LICENSE
